matplotloom/__init__.py
matplotloom/loom.py
matplotloom-0.9.0.dist-info/METADATA
matplotloom-0.9.0.dist-info/WHEEL
matplotloom-0.9.0.dist-info/licenses/LICENSE
matplotloom-0.9.0.dist-info/RECORD
