Metadata-Version: 2.4
Name: matplotloom
Version: 0.9.0
Summary: Weave your frames into matplotlib animations.
Author-email: ali-ramadhan <ali.hh.ramadhan@gmail.com>
License-Expression: MIT
License-File: LICENSE
Requires-Python: >=3.10
Requires-Dist: ipython>=8.37.0
Requires-Dist: matplotlib>=3.10.3
